strawberry_jam/__init__.py
strawberry_jam/chunks/__init__.py
strawberry_jam/chunks/query_set_managers/__init__.py
strawberry_jam/chunks/query_set_managers/templates/__init__.py
strawberry_jam/chunks/query_set_managers/templates/node.py
strawberry_jam/chunks/query_set_managers/templates/query_set_manager.py
strawberry_jam/chunks/query_tests/__init__.py
strawberry_jam/chunks/query_tests/templates/query_test.py
strawberry_jam/chunks/query_tests/templates/schema_is_valid_test.py
strawberry_jam/chunks/relay_mutations/__init__.py
strawberry_jam/chunks/relay_mutations/templates/create_input.py
strawberry_jam/chunks/relay_mutations/templates/mutation.py
strawberry_jam/chunks/relay_mutations/templates/schema.py
strawberry_jam/chunks/relay_mutations/templates/update_input.py
strawberry_jam/chunks/relay_queries/templates/__init__.py
strawberry_jam/chunks/relay_queries/templates/filter.py
strawberry_jam/chunks/relay_queries/templates/node.py
strawberry_jam/chunks/relay_queries/templates/order.py
strawberry_jam/chunks/relay_queries/templates/query.py
strawberry_jam/chunks/relay_queries/templates/schema.py
strawberry_jam/chunks/relay_queries/templates/urls.py
strawberry_jam/conventions.py
strawberry_jam/forms.py
strawberry_jam/management/__init__.py
strawberry_jam/management/commands/__init__.py
strawberry_jam/management/commands/configure-schema.py
strawberry_jam/mutations.py
strawberry_jam/queryset.py
strawberry_jam/template.py
strawberry_jam/utils.py
strawberry_jam-1.1.0.dist-info/LICENSE
strawberry_jam-1.1.0.dist-info/METADATA
strawberry_jam-1.1.0.dist-info/WHEEL
strawberry_jam-1.1.0.dist-info/RECORD
