Metadata-Version: 2.1
Name: strawberry_jam
Version: 1.1.0
Summary: Codegen django command for strawberry-django for rapid schema boilerplate generation from given models
Home-page: https://github.com/Elawphant/strawberry_jam
License: MIT
Keywords: graphql,django,strawberry-graphql-django,command
Author: Gevorg Hakobyan
Author-email: gevorg.hakobyan@elawphant.am
Requires-Python: >=3.8
Classifier: License :: OSI Approved :: MIT License
Classifier: Programming Language :: Python :: 3
Classifier: Programming Language :: Python :: 3.8
Classifier: Programming Language :: Python :: 3.9
Classifier: Programming Language :: Python :: 3.10
Classifier: Programming Language :: Python :: 3.11
Classifier: Programming Language :: Python :: 3.12
Requires-Dist: aiohttp (>=3.8.1,<4.0.0)
Requires-Dist: django (>=4.0.0,<5.0.0)
Requires-Dist: pytest (>=8.2.1,<9.0.0)
Requires-Dist: strawberry-graphql-django (>=0.44.1,<0.45.0)
Requires-Dist: tqdm (>=4.50.0,<5.0.0)
Project-URL: Repository, https://github.com/Elawphant/strawberry_jam
